{
  "permissions": {
    "storage": {
      "mobiusevoUserfiles": [
        "create",
        "read",
        "update",
        "delete"
      ],
      "Job:@model(appsync)": [
        "create",
        "read",
        "update",
        "delete"
      ],
      "GenEvalParam:@model(appsync)": [
        "create",
        "read",
        "update",
        "delete"
      ]
    }
  },
  "lambdaLayers": [
    {
      "type": "ProjectLayer",
      "resourceName": "evoBackend",
      "version": 3
    }
  ]
}